sea_query-0.2.5.dist-info/METADATA
sea_query-0.2.5.dist-info/WHEEL
sea_query-0.2.5.dist-info/licenses/LICENSE
sea_query/mysql.py
sea_query/query.py
sea_query/table.py
sea_query/__init__.py
sea_query/foreign_key.py
sea_query/sqlite.py
sea_query/_internal.pyi
sea_query/postgres.py
sea_query/index.py
sea_query/expr.py
sea_query/py.typed
sea_query/_internal.cpython-310-powerpc64le-linux-gnu.so
sea_query-0.2.5.dist-info/RECORD
