Metadata-Version: 2.3
Name: sea-query
Version: 0.2.5
Classifier: Topic :: Database
Classifier: Topic :: Software Development :: Libraries
Classifier: Development Status :: 3 - Alpha
Classifier: Programming Language :: Python :: 3.8
Classifier: Programming Language :: Python :: 3.9
Classifier: Programming Language :: Python :: 3.10
Classifier: Programming Language :: Python :: 3.11
Classifier: Programming Language :: Python :: 3.12
Classifier: Programming Language :: Rust
Classifier: Programming Language :: Python :: Implementation :: CPython
Classifier: Programming Language :: Python :: Implementation :: PyPy
Classifier: Typing :: Stubs Only
License-File: LICENSE
Summary: Query builder to help you construct dynamic SQL queries
Author-email: Ordanis Sanchez <sea-query@ordanisanchez.dev>
Requires-Python: >=3.8
Project-URL: Repository, https://github.com/oldani/sea-query/
